{
  "slug": "adaptive-functioning",
  "term": "Adaptive Functioning",
  "definition": "A person's practical ability to perform everyday tasks and navigate daily life independently, such as managing money, communicating effectively, maintaining employment, and caring for oneself. It is one of the three diagnostic criteria for intellectual disability alongside IQ and age of onset.",
  "examples": [
    "Respondent's experts pointed to Smith's struggles with reading, financial management, and independent living as evidence of deficits in adaptive functioning."
  ],
  "relatedTerms": [
    "Intellectual Disability",
    "Prong 2"
  ]
}