{
  "slug": "constructive-denial",
  "term": "Constructive denial",
  "definition": "A situation where, although there is no explicit refusal to provide something, the conditions or circumstances effectively deny access. In Title IX, a constructive denial of educational opportunity can constitute discrimination even without a formal exclusion.",
  "examples": [
    "B.P.J.'s counsel argued that being told to play on the boys' team, which conflicts with her gender identity, amounts to a constructive denial of all athletic opportunity."
  ],
  "relatedTerms": [
    "constructive discharge",
    "equal athletic opportunity"
  ]
}