{
  "slug": "executive-authority",
  "term": "Executive Authority",
  "definition": "The constitutional and statutory powers vested in the President and executive branch agencies to enforce laws, conduct foreign relations, and manage government operations. The scope of this authority is defined by the Constitution and statutes passed by Congress.",
  "examples": [
    "The Attorney General's authority to direct federal law enforcement and immigration enforcement activities"
  ],
  "relatedTerms": [
    "Prosecutorial Discretion",
    "Separation of Powers"
  ]
}