{
  "slug": "patent-infringement",
  "term": "Patent Infringement",
  "definition": "The unauthorized making, using, offering to sell, or selling of a patented invention during the patent term. In patent law, a party infringes if it makes, uses, or sells a product or process covered by a valid patent claim without permission.",
  "examples": [
    "A generic pharmaceutical manufacturer infringes if it produces a drug covered by an active patent without a license"
  ],
  "relatedTerms": [
    "Patent validity",
    "Patent claims"
  ]
}