{
  "slug": "right-to-assistance-of-counsel",
  "term": "Right to assistance of counsel",
  "definition": "The Sixth Amendment guarantee that a criminal defendant has the right to have a lawyer help with their defense. This includes not just having a lawyer present but receiving meaningful legal advice and assistance on trial-related matters.",
  "examples": [
    "Villarreal's right to consult with his attorney during an overnight recess about trial strategy, plea options, and other matters"
  ],
  "relatedTerms": [
    "Sixth Amendment",
    "Effective assistance of counsel"
  ]
}