{
  "slug": "tax-foreclosure",
  "term": "Tax Foreclosure",
  "definition": "A legal process by which a government seizes and sells a person's property when the owner fails to pay property taxes. The sale proceeds are used to satisfy the unpaid tax debt, and any leftover money is the 'surplus.'",
  "examples": [
    "Isabella County used Michigan's tax foreclosure law to take Timothy Pung's property after he fell behind on his taxes, then kept all the sale proceeds instead of returning the surplus to his estate."
  ],
  "relatedTerms": [
    "Surplus Equity",
    "Redemption Period"
  ]
}