{
  "slug": "fcc-v-pacifica-foundation",
  "name": "FCC v. Pacifica Foundation",
  "citation": "438 U.S. 726",
  "year": 1978,
  "summary": "The Court upheld FCC sanctions against a radio station for broadcasting George Carlin's 'Filthy Words' monologue in the daytime, applying reduced First Amendment protection to broadcast media because of its pervasive, uninvited presence in homes and the use of publicly licensed airwaves.",
  "significance": "Texas argued that Pacifica's reduced scrutiny for broadcast media could be analogized to internet regulation; petitioners and the government distinguished it as limited to over-the-air broadcasting's unique pervasiveness and spectrum scarcity, which have no internet counterpart.",
  "topics": []
}