{
  "slug": "lora-v-united-states",
  "name": "Lora v. United States",
  "year": 2024,
  "summary": "Held that § 924(j)'s penalties stand independently from § 924(c) and do not incorporate § 924(c)'s mandatory minimums or consecutive sentencing mandates, as Congress designed § 924(j) to account for the seriousness of killing by itself.",
  "significance": "Central to the case. The Court held that § 924(j) has its own independent penalty scheme that does not incorporate § 924(c)'s mandatory minimums or consecutive sentencing requirements. The Second Circuit relied on Lora to conclude these are separate offenses, while petitioner argues Lora supports the opposite conclusion.",
  "topics": []
}