{
  "slug": "morrison-v-olson",
  "name": "Morrison v. Olson",
  "citation": "487 U.S. 654",
  "year": 1988,
  "summary": "Upheld the independent counsel statute's removal restrictions under a functional balancing test, rejecting the rigid categorical approach of Humphrey's Executor.",
  "significance": "Petitioners argued it repudiated Humphrey's Executor's quasi-legislative/quasi-judicial reasoning; cited as part of the evolving and unstable framework around removal restrictions.",
  "topics": []
}