{
  "slug": "myers-v-united-states",
  "name": "Myers v. United States",
  "citation": "272 U.S. 52",
  "year": 1926,
  "summary": "Held that the President has constitutional authority to remove a postmaster without Senate consent, finding that the removal power is incident to the executive power.",
  "significance": "Petitioners cited it as establishing the President's broad removal power; respondents noted that four Myers justices later joined the unanimous Humphrey's Executor decision.",
  "topics": []
}