{
  "slug": "national-institute-of-family-and-life-advocates-v-becerra-nifla",
  "name": "National Institute of Family and Life Advocates v. Becerra (NIFLA)",
  "citation": "585 U.S. 755",
  "year": 2018,
  "summary": "The Court struck down a California law requiring crisis pregnancy centers to provide certain notices, holding there is no separate category of 'professional speech' exempt from ordinary First Amendment scrutiny.",
  "significance": "Central to the dispute — petitioner argued NIFLA rejected a 'professional speech' exception to the First Amendment and warned against state manipulation of professional-client conversations. Respondent tried to distinguish it as broader than the narrow healthcare treatment context at issue here.",
  "topics": []
}